{
  "fields": [
    {
      "aggregatable": true,
      "custom": false,
      "defaultValue": null,
      "extraTypeInfo": null,
      "filterable": true,
      "groupable": true,
      "inlineHelpText": null,
      "label": "ID de la licence du package de l'utilisateur",
      "name": "Id",
      "nillable": false,
      "picklistValues": [],
      "referenceTo": [],
      "relationshipName": null,
      "sortable": true,
      "type": "id"
    },
    {
      "aggregatable": true,
      "custom": false,
      "defaultValue": null,
      "extraTypeInfo": null,
      "filterable": true,
      "groupable": true,
      "inlineHelpText": null,
      "label": "ID de la licence du package",
      "name": "PackageLicenseId",
      "nillable": false,
      "picklistValues": [],
      "referenceTo": [
        "PackageLicense"
      ],
      "relationshipName": "PackageLicense",
      "sortable": true,
      "type": "reference"
    },
    {
      "aggregatable": true,
      "custom": false,
      "defaultValue": null,
      "extraTypeInfo": null,
      "filterable": true,
      "groupable": true,
      "inlineHelpText": null,
      "label": "ID utilisateur attribué",
      "name": "UserId",
      "nillable": false,
      "picklistValues": [],
      "referenceTo": [
        "User"
      ],
      "relationshipName": null,
      "sortable": true,
      "type": "reference"
    },
    {
      "aggregatable": true,
      "custom": false,
      "defaultValue": null,
      "extraTypeInfo": null,
      "filterable": true,
      "groupable": false,
      "inlineHelpText": null,
      "label": "Date de création",
      "name": "CreatedDate",
      "nillable": false,
      "picklistValues": [],
      "referenceTo": [],
      "relationshipName": null,
      "sortable": true,
      "type": "datetime"
    },
    {
      "aggregatable": true,
      "custom": false,
      "defaultValue": null,
      "extraTypeInfo": null,
      "filterable": true,
      "groupable": true,
      "inlineHelpText": null,
      "label": "ID créé par",
      "name": "CreatedById",
      "nillable": false,
      "picklistValues": [],
      "referenceTo": [
        "User"
      ],
      "relationshipName": "CreatedBy",
      "sortable": true,
      "type": "reference"
    },
    {
      "aggregatable": true,
      "custom": false,
      "defaultValue": null,
      "extraTypeInfo": null,
      "filterable": true,
      "groupable": false,
      "inlineHelpText": null,
      "label": "Date de dernière modification",
      "name": "LastModifiedDate",
      "nillable": false,
      "picklistValues": [],
      "referenceTo": [],
      "relationshipName": null,
      "sortable": true,
      "type": "datetime"
    },
    {
      "aggregatable": true,
      "custom": false,
      "defaultValue": null,
      "extraTypeInfo": null,
      "filterable": true,
      "groupable": true,
      "inlineHelpText": null,
      "label": "ID dernière modification par",
      "name": "LastModifiedById",
      "nillable": false,
      "picklistValues": [],
      "referenceTo": [
        "User"
      ],
      "relationshipName": "LastModifiedBy",
      "sortable": true,
      "type": "reference"
    },
    {
      "aggregatable": true,
      "custom": false,
      "defaultValue": null,
      "extraTypeInfo": null,
      "filterable": true,
      "groupable": false,
      "inlineHelpText": null,
      "label": "Horodateur des modifications du système",
      "name": "SystemModstamp",
      "nillable": false,
      "picklistValues": [],
      "referenceTo": [],
      "relationshipName": null,
      "sortable": true,
      "type": "datetime"
    }
  ],
  "label": "Licence du package de l'utilisateur",
  "childRelationships": [],
  "custom": false,
  "name": "UserPackageLicense",
  "queryable": true
}